pixelpacker/__init__.py
pixelpacker/cli.py
pixelpacker/core.py
pixelpacker/crop.py
pixelpacker/data_models.py
pixelpacker/io_utils.py
pixelpacker/limits.py
pixelpacker/manifest.py
pixelpacker/processing.py
pixelpacker/stretch.py
pixelpacker/utils.py
pixelpacker/tests/conftest.py
pixelpacker/tests/test_cli.py
pixelpacker/tests/test_io_utils.py
pixelpacker/tests/test_manifest.py
pixelpacker/tests/test_mock_pipeline.py
pixelpacker/tests/test_pipeline.py
pixelpacker/tests/test_stretch.py
pixelpacker-0.3.0.dist-info/licenses/LICENSE
pixelpacker-0.3.0.dist-info/METADATA
pixelpacker-0.3.0.dist-info/WHEEL
pixelpacker-0.3.0.dist-info/entry_points.txt
pixelpacker-0.3.0.dist-info/top_level.txt
pixelpacker-0.3.0.dist-info/RECORD
