Metadata-Version: 2.4
Name: pixelpacker
Version: 0.3.0
Summary: Automates TIFF stack processing: autoscale, convert to 8‑bit, tile 3D volumes into 2D atlases, and compress to WebP for web‑based volumetric viewing.
Author-email: Brandon Scott <brandon.scott@sdsmt.edu>
License: MIT License
Project-URL: Homepage, https://github.com/bscott711/PixelPacker
Project-URL: Source, https://github.com/bscott711/PixelPacker
Project-URL: Tracker, https://github.com/bscott711/PixelPacker/issues
Keywords: tiff,webp,volumetric,atlas,imaging,pipeline
Classifier: Programming Language :: Python :: 3
Classifier: Programming Language :: Python :: 3.10
Classifier: Programming Language :: Python :: 3.11
Classifier: Programming Language :: Python :: 3.12
Classifier: License :: OSI Approved :: MIT License
Classifier: Operating System :: OS Independent
Classifier: Development Status :: 3 - Alpha
Classifier: Intended Audience :: Science/Research
Classifier: Topic :: Scientific/Engineering :: Image Processing
Requires-Python: >=3.10
License-File: LICENSE
Requires-Dist: typer>=0.9.0
Requires-Dist: matplotlib<4.0,>=3.7
Requires-Dist: numpy<3.0,>=1.21
Requires-Dist: pillow<12.0,>=10.0
Requires-Dist: scipy<2.0,>=1.7
Requires-Dist: tifffile>=2023.1.1
Requires-Dist: tqdm>=4.64
Requires-Dist: typing_extensions>=4.0.0
Requires-Dist: pyyaml>=6.0
Requires-Dist: scikit-image>=0.19
Provides-Extra: test
Requires-Dist: pytest>=7.0; extra == "test"
Requires-Dist: pytest-html>=4.0; extra == "test"
Requires-Dist: pytest-xdist>=3.0; extra == "test"
Requires-Dist: pytest-cov>=3.0; extra == "test"
Requires-Dist: pytest-mock>=3.10; extra == "test"
Provides-Extra: dev
Requires-Dist: pixelpacker[test]; extra == "dev"
Requires-Dist: ruff; extra == "dev"
Requires-Dist: pre-commit>=3.0.0; extra == "dev"
Requires-Dist: build>=1.2.0; extra == "dev"
Requires-Dist: twine>=6.0.0; extra == "dev"
Requires-Dist: snakeviz>=2.2.0; extra == "dev"
Dynamic: license-file
